cfile_txt_pkg/__init__.py
cfile_txt_pkg/cfile_txt.py
createf_txt_example_pkg8-0.0.0.8.dist-info/LICENSE
createf_txt_example_pkg8-0.0.0.8.dist-info/METADATA
createf_txt_example_pkg8-0.0.0.8.dist-info/WHEEL
createf_txt_example_pkg8-0.0.0.8.dist-info/top_level.txt
createf_txt_example_pkg8-0.0.0.8.dist-info/RECORD
